oceancrow_scaffolder/__init__.py
oceancrow_scaffolder/oceancrow_scaffolder.py
oceancrow_scaffolder/templates/app.py
oceancrow_scaffolder/templates/main.py
oceancrow_scaffolder/templates/notebook.py
oceancrow_scaffolder/templates/requirements_datascience.txt
oceancrow_scaffolder/templates/requirements_flask.txt
oceancrow_scaffolder-0.1.0.dist-info/licenses/LICENSE.txt
oceancrow_scaffolder-0.1.0.dist-info/METADATA
oceancrow_scaffolder-0.1.0.dist-info/WHEEL
oceancrow_scaffolder-0.1.0.dist-info/entry_points.txt
oceancrow_scaffolder-0.1.0.dist-info/top_level.txt
oceancrow_scaffolder-0.1.0.dist-info/RECORD
