Metadata-Version: 2.4
Name: OceanCrow_Scaffolder
Version: 0.1.0
Summary: A Python project scaffolding tool by Sheldon Kenny Salmon (@OceanCrowtt)
Author-email: Sheldon Kenny Salmon <oceancrowtt@gmail.com>
License: MIT
Classifier: Programming Language :: Python :: 3
Classifier: License :: OSI Approved :: MIT License
Classifier: Operating System :: OS Independent
License-File: LICENSE.txt
Requires-Dist: click>=8.1.0
Dynamic: license-file
